eas/__init__.py
eas/__main__.py
eas/attestation_converter.py
eas/cli.py
eas/config.py
eas/converters.py
eas/core.py
eas/exceptions.py
eas/observability.py
eas/query.py
eas/schema_encoder.py
eas/schema_generator.py
eas/schema_registry.py
eas/security.py
eas/transaction.py
eas/type_parser.py
eas/types.py
eas/contracts/__init__.py
eas/contracts/eas-abi.json
eas/v1/__init__.py
eas/v1/messages_pb2.py
eas/v1/messages_pb2.pyi
eas/v1/messages_pb2_grpc.py
eas_sdk-0.1.6.dist-info/licenses/LICENSE
eas_sdk-0.1.6.dist-info/METADATA
eas_sdk-0.1.6.dist-info/WHEEL
eas_sdk-0.1.6.dist-info/entry_points.txt
eas_sdk-0.1.6.dist-info/top_level.txt
eas_sdk-0.1.6.dist-info/RECORD
