Metadata-Version: 2.4
Name: eas-sdk
Version: 0.1.6
Summary: Python SDK for Ethereum Attestation Service (EAS)
Author: EAS SDK Contributors
License: MIT
Project-URL: Homepage, https://github.com/cyberstorm-dev/eas-sdk-python
Project-URL: Repository, https://github.com/cyberstorm-dev/eas-sdk-python
Project-URL: Documentation, https://github.com/cyberstorm-dev/eas-sdk-python#readme
Project-URL: Bug Tracker, https://github.com/cyberstorm-dev/eas-sdk-python/issues
Keywords: ethereum,attestation,web3,blockchain,eas
Classifier: Development Status :: 3 - Alpha
Classifier: Intended Audience :: Developers
Classifier: License :: OSI Approved :: MIT License
Classifier: Programming Language :: Python :: 3
Classifier: Programming Language :: Python :: 3.11
Classifier: Programming Language :: Python :: 3.12
Classifier: Topic :: Software Development :: Libraries :: Python Modules
Classifier: Topic :: Internet :: WWW/HTTP
Classifier: Topic :: Security :: Cryptography
Requires-Python: >=3.11
License-File: LICENSE
Requires-Dist: protobuf>=6.32.0
Requires-Dist: web3>=6.14.0
Requires-Dist: jsonschema>=4.25.1
Requires-Dist: eth-abi>=5.2.0
Requires-Dist: python-dotenv
Requires-Dist: PyYAML
Requires-Dist: requests
Requires-Dist: rich
Requires-Dist: click
Requires-Dist: grpcio-tools
Requires-Dist: grpcio-status
Requires-Dist: structlog
Requires-Dist: pydantic>=2.0.0
Provides-Extra: dev
Requires-Dist: pytest>=7.0.0; extra == "dev"
Requires-Dist: pytest-cov>=4.0.0; extra == "dev"
Requires-Dist: black>=23.0.0; extra == "dev"
Requires-Dist: isort>=5.12.0; extra == "dev"
Requires-Dist: flake8>=6.0.0; extra == "dev"
Requires-Dist: mypy>=1.0.0; extra == "dev"
Requires-Dist: mypy-protobuf>=3.6.0; extra == "dev"
Requires-Dist: types-PyYAML; extra == "dev"
Requires-Dist: types-protobuf; extra == "dev"
Requires-Dist: types-requests; extra == "dev"
Requires-Dist: build>=1.0.0; extra == "dev"
Requires-Dist: twine>=4.0.0; extra == "dev"
Dynamic: license-file
